gs_ai_package/__init__.py
gs_ai_package/direction_processor.py
gs_ml_toolkit/__init__.py
gs_ml_toolkit/direction_processor.py
gs_ml_toolkit/gtfs_merger.py
gs_ml_toolkit-0.1.3.dist-info/METADATA
gs_ml_toolkit-0.1.3.dist-info/WHEEL
gs_ml_toolkit-0.1.3.dist-info/top_level.txt
gs_ml_toolkit-0.1.3.dist-info/RECORD
