Metadata-Version: 2.1
Name: gs_ml_toolkit
Version: 0.1.3
Summary: Package per trattare dati di trasporto pubblico e semplificare l'utilizzo di questi in progetti AI
Home-page: https://gitlab.greenshare.it/rombo-ai/gs_ml_toolkit.git
Author: PietroCosseddu
Author-email: pietro.cosseddu@green-share.it
Classifier: Programming Language :: Python :: 3
Classifier: Operating System :: OS Independent
Requires-Python: >=3.7
Requires-Dist: pandas>=1.0.0
Requires-Dist: numpy>=1.18.0
